Metadata-Version: 1.1
Name: macoop
Version: 0.0.1
Summary: Create For Learing Only!!
Home-page: https://github.com/maxmonamimai/
Author: MC CHAKKRAPONG
Author-email: furbierecords2@gmail.com
License: MIT
Download-URL: https://github.com/maxmonamimai/macoop/archive/v0.0.1.zip
Keywords: oop,macoop,MC CHAKKRAPONG
Platform: UNKNOWN
Classifier: Development Status :: 3 - Alpha
Classifier: Intended Audience :: Education
Classifier: Topic :: Software Development :: Build Tools
Classifier: License :: OSI Approved :: MIT License
Classifier: Programming Language :: Python :: 3
Classifier: Programming Language :: Python :: 3.4
Classifier: Programming Language :: Python :: 3.5
Classifier: Programming Language :: Python :: 3.6
Classifier: Programming Language :: Python :: 3.7
Classifier: Programming Language :: Python :: 3.8
Classifier: Programming Language :: Python :: 3.9
